[
  {
    "row": 58,
    "sku": "CA24-14-CASA-MAGNA-XV",
    "msrpUsd": 12,
    "lengthIn": 6.0,
    "ringGauge": 54,
    "shape": "Toro",
    "stickSize": "6 × 54 · Toro",
    "smokeBand": "long",
    "catalogLine": "Casa Magna Colorado XV Anniversary · 6 × 54 · Toro · Medium-Full · Nicaragua · $12 · Notes: cedar, wood, earth, leather",
    "memberBlurb": "Colorado XV anniversary — woody Nicaraguan core with celebration-tier richness. Solid bourbon companion.",
    "priceNote": "",
    "sizeNote": ""
  },
  {
    "row": 59,
    "sku": "CA24-15-RYJ-WIDE",
    "msrpUsd": 11,
    "lengthIn": 7.0,
    "ringGauge": 58,
    "shape": "Churchill",
    "stickSize": "7 × 58 · Churchill",
    "smokeBand": "session",
    "catalogLine": "Romeo y Julieta Wide Churchill · 7 × 58 · Churchill · Medium · Dominican · $11 · Notes: cedar, wood, earth, leather",
    "memberBlurb": "Wide Churchill format — Indonesian wrapper and long, easy-burning Dominican session. Mild-to-medium crowd-pleaser.",
    "priceNote": "",
    "sizeNote": ""
  },
  {
    "row": 60,
    "sku": "CA24-16-PERDOMO-30-SG",
    "msrpUsd": 13,
    "lengthIn": 6.0,
    "ringGauge": 54,
    "shape": "Toro",
    "stickSize": "6 × 54 · Toro",
    "smokeBand": "long",
    "catalogLine": "Perdomo 30th Anniversary Sun Grown Epicure · 6 × 54 · Toro · Medium-Full · Nicaragua · $13 · Notes: cedar, baking spice, sweet tobacco, toast",
    "memberBlurb": "Perdomo 30th sun-grown — Ecuador wrapper sweetness over Nicaraguan filler. Anniversary smoke with approachable MSRP.",
    "priceNote": "",
    "sizeNote": ""
  },
  {
    "row": 61,
    "sku": "CA24-17-PLAS-151",
    "msrpUsd": 14,
    "lengthIn": 5.5,
    "ringGauge": 50,
    "shape": "Robusto",
    "stickSize": "5½ × 50 · Robusto",
    "smokeBand": "standard",
    "catalogLine": "Plasencia Cosecha 151 La Musica · 5½ × 50 · Robusto · Medium-Full · Nicaragua · $14 · Notes: cedar, wood, earth, leather",
    "memberBlurb": "Plasencia Cosecha 151 — Nicaraguan puro wood and rum-friendly spice. Heritage grower brand in a classic robusto.",
    "priceNote": "",
    "sizeNote": ""
  },
  {
    "row": 62,
    "sku": "CA24-18-601-WARHEAD",
    "msrpUsd": 12,
    "lengthIn": 5.0,
    "ringGauge": 56,
    "shape": "Robusto",
    "stickSize": "5 × 56 · Robusto",
    "smokeBand": "standard",
    "catalogLine": "601 La Bomba Warhead X · 5 × 56 · Robusto · Full · Nicaragua · $12 · Notes: cocoa, earth, pepper, espresso",
    "memberBlurb": "La Bomba Warhead X — 56-ring Nicaraguan power in a short format. Experienced smokers only; not a beginner flex.",
    "priceNote": "",
    "sizeNote": ""
  },
  {
    "row": 63,
    "sku": "CA24-19-HERRERA-NORTENO",
    "msrpUsd": 11,
    "lengthIn": 7.0,
    "ringGauge": 44,
    "shape": "Lonsdale",
    "stickSize": "7 × 44 · Lonsdale",
    "smokeBand": "long",
    "catalogLine": "Herrera Esteli Norteño · 7 × 44 · Lonsdale · Medium-Full · Nicaragua · $11 · Notes: earth, savory spice, cedar, cocoa",
    "memberBlurb": "Drew Estate Norteño — Mexican San Andrés over Nicaraguan core in a lonsdale. Savory lonsdale for bourbon after dinner.",
    "priceNote": "",
    "sizeNote": ""
  },
  {
    "row": 64,
    "sku": "CA24-20-COHIBA-RIVIERA",
    "msrpUsd": 12,
    "lengthIn": 5.0,
    "ringGauge": 50,
    "shape": "Robusto",
    "stickSize": "5 × 50 · Robusto",
    "smokeBand": "standard",
    "catalogLine": "Cohiba Riviera · 5 × 50 · Robusto · Medium · Dominican · $12 · Notes: cream, cedar, nuts, toast",
    "memberBlurb": "U.S. Cohiba Riviera — Connecticut shade cream and approachable Dominican body. Legal shelf Cohiba name, not island Cuban.",
    "priceNote": "U.S. General Cigar Cohiba — not island Cuban.",
    "sizeNote": ""
  },
  {
    "row": 65,
    "sku": "CA24-21-LFD-CHISELITO",
    "msrpUsd": 14,
    "lengthIn": 5.5,
    "ringGauge": 54,
    "shape": "Chisel",
    "stickSize": "5½ × 54 · Chisel",
    "smokeBand": "standard",
    "catalogLine": "La Flor Dominicana Double Ligero Chiselito Maduro · 5½ × 54 · Chisel · Full · Dominican · $14 · Notes: cocoa, earth, pepper, espresso",
    "memberBlurb": "Double Ligero in Chiselito maduro — broadleaf cocoa and pepper in the signature LFD shape. Shorter than full Chisel DL.",
    "priceNote": "",
    "sizeNote": "Chiselito format; L4-LFD-DL is full Chisel Double Ligero."
  },
  {
    "row": 66,
    "sku": "CA24-22-ONEOFF-BT",
    "msrpUsd": 12,
    "lengthIn": 5.0,
    "ringGauge": 50,
    "shape": "Robusto",
    "stickSize": "5 × 50 · Robusto",
    "smokeBand": "standard",
    "catalogLine": "OneOff Black & Tan · 5 × 50 · Robusto · Medium-Full · Nicaragua · $12 · Notes: earth, savory spice, cedar, cocoa",
    "memberBlurb": "OneOff Black & Tan robusto — layered Aganorsa savory character in a 5×50. Related to OneOff Black toro on 2025 list, different blend.",
    "priceNote": "",
    "sizeNote": "Black & Tan blend; CA25-20 is OneOff Black Toro."
  },
  {
    "row": 67,
    "sku": "CA24-23-WARPED-CORTO",
    "msrpUsd": 11,
    "lengthIn": 4.5,
    "ringGauge": 52,
    "shape": "Petit Toro",
    "stickSize": "4½ × 52 · Petit Toro",
    "smokeBand": "standard",
    "catalogLine": "Warped Corto X52 · 4½ × 52 · Petit Toro · Medium-Full · Nicaragua · $11 · Notes: cedar, baking spice, sweet tobacco, toast",
    "memberBlurb": "Warped Corto X52 — concentrated Nicaraguan spice in a 4½-inch petit format. Big flavor when time is tight.",
    "priceNote": "",
    "sizeNote": ""
  },
  {
    "row": 68,
    "sku": "CA24-24-FERIO-SUMMA",
    "msrpUsd": 13,
    "lengthIn": 5.625,
    "ringGauge": 46,
    "shape": "Corona Gorda",
    "stickSize": "5.625 × 46 · Corona Gorda",
    "smokeBand": "standard",
    "catalogLine": "Ferio Tego Summa · 5.625 × 46 · Corona Gorda · Medium-Full · Nicaragua · $13 · Notes: cedar, wood, earth, leather",
    "memberBlurb": "Ferio Tego Summa corona gorda — Plasencia-made Nicaraguan wood and polish. Sister brand to Timeless Supreme on the 2025 list.",
    "priceNote": "",
    "sizeNote": "Summa line; CA25-10 is Timeless Supreme 650."
  },
  {
    "row": 69,
    "sku": "CA24-25-TAT-RES-A1",
    "msrpUsd": 14,
    "lengthIn": 6.75,
    "ringGauge": 38,
    "shape": "Lancero",
    "stickSize": "6¾ × 38 · Lancero",
    "smokeBand": "long",
    "catalogLine": "Tatuaje Reserva A Uno · 6¾ × 38 · Lancero · Medium-Full · Nicaragua · $14 · Notes: cedar, wood, earth, leather",
    "memberBlurb": "Tatuaje Reserva A Uno lancero — focused Nicaraguan spice and cedar in a 38-ring. Experienced smokers who like precision formats.",
    "priceNote": "",
    "sizeNote": ""
  },
  {
    "row": 70,
    "sku": "CUR-01-HOYO-SANJUAN",
    "msrpUsd": 0,
    "lengthIn": 5.875,
    "ringGauge": 46,
    "shape": "Corona Gorda",
    "stickSize": "5.875 × 46 · Corona Gorda",
    "smokeBand": "standard",
    "catalogLine": "Hoyo de Monterrey Le Hoyo de San Juan · 5.875 × 46 · Corona Gorda · Medium · Cuban · — · Notes: cedar, wood, earth, leather",
    "memberBlurb": "Elegant Cuban Hoyo - cedar, cream, and gentle sweetness in a long corona gorda. Benchmark medium Habanos for Scotch evenings.",
    "priceNote": "Island Cuban; not U.S. retail MSRP.",
    "sizeNote": ""
  },
  {
    "row": 71,
    "sku": "CUR-02-EPC-MAJESTIC",
    "msrpUsd": 16,
    "lengthIn": 6.0,
    "ringGauge": 58,
    "shape": "Toro Gordo",
    "stickSize": "6 × 58 · Toro Gordo",
    "smokeBand": "long",
    "catalogLine": "E.P. Carrillo Encore Majestic · 6 × 58 · Toro Gordo · Medium-Full · Nicaragua · $16 · Notes: cedar, wood, earth, leather",
    "memberBlurb": "Encore at full toro gordo scale - woody Nicaraguan puro depth and celebration body. Bigger step up from the Celestial on the 2024 list.",
    "priceNote": "",
    "sizeNote": "Encore line; CA24-03 is Celestial vitola."
  },
  {
    "row": 72,
    "sku": "CUR-03-AF-ROSADO-52",
    "msrpUsd": 14,
    "lengthIn": 6.0,
    "ringGauge": 52,
    "shape": "Toro",
    "stickSize": "6 × 52 · Toro",
    "smokeBand": "long",
    "catalogLine": "Arturo Fuente Rosado Sungrown Fifty-Two · 6 × 52 · Toro · Medium-Full · Dominican · $14 · Notes: cedar, baking spice, sweet tobacco, toast",
    "memberBlurb": "Fuente rosado sungrown spice - cedar, red pepper, and polished Ecuador wrapper over classic Dominican core. Special-occasion Fuente without OpusX.",
    "priceNote": "",
    "sizeNote": ""
  },
  {
    "row": 73,
    "sku": "CUR-04-COHIBA-PIR-E",
    "msrpUsd": 0,
    "lengthIn": 6.375,
    "ringGauge": 54,
    "shape": "Pirámide",
    "stickSize": "6.375 × 54 · Pirámide",
    "smokeBand": "long",
    "catalogLine": "Cohiba Pirámides Extra · 6.375 × 54 · Pirámide · Medium-Full · Cuban · — · Notes: caramel, cream, oak, almond",
    "memberBlurb": "Island Cohiba piramide - cocoa, leather, and refined Cuban luxury in a tapered format. Collector Cuban only.",
    "priceNote": "Island Cuban; not U.S. retail MSRP.",
    "sizeNote": ""
  },
  {
    "row": 74,
    "sku": "CUR-05-OPUSX-RDC",
    "msrpUsd": 32,
    "lengthIn": 7.0,
    "ringGauge": 48,
    "shape": "Churchill",
    "stickSize": "7 × 48 · Churchill",
    "smokeBand": "session",
    "catalogLine": "Arturo Fuente Fuente Fuente OpusX · 7 × 48 · Churchill · Full · Dominican · $32 · Notes: cedar, baking spice, sweet tobacco, toast",
    "memberBlurb": "The classic OpusX Reserva d'Chateau - Dominican puro prestige, cedar, fruit, and baking spice in a 7x48 Churchill. Not the Angel's Share variant.",
    "priceNote": "",
    "sizeNote": "Classic OpusX RdC; CA25-09 is Angel's Share variant."
  },
  {
    "row": 75,
    "sku": "CUR-06-AF-DCHATEAU",
    "msrpUsd": 9,
    "lengthIn": 6.75,
    "ringGauge": 54,
    "shape": "Toro",
    "stickSize": "6¾ × 54 · Toro",
    "smokeBand": "long",
    "catalogLine": "Arturo Fuente Chateau Fuente Double · 6¾ × 54 · Toro · Medium · Dominican · $9 · Notes: cream, cedar, nuts, toast",
    "memberBlurb": "Double Chateau Connecticut - cream, nuts, and easy Fuente balance in a longer 54-ring smoke. Approachable premium afternoon.",
    "priceNote": "",
    "sizeNote": "Distinct from Gran Reserva Chateau in L3-AF-GRANRES."
  },
  {
    "row": 76,
    "sku": "CUR-07-FDLA-TG",
    "msrpUsd": 11,
    "lengthIn": 6.5,
    "ringGauge": 58,
    "shape": "Toro Gordo",
    "stickSize": "6½ × 58 · Toro Gordo",
    "smokeBand": "long",
    "catalogLine": "Flor de las Antillas · 6½ × 58 · Toro Gordo · Medium-Full · Nicaragua · $11 · Notes: cedar, baking spice, sweet tobacco, toast",
    "memberBlurb": "Jose Garcia award-winner - sweet spice, cedar, and Nicaraguan sun-grown richness in a 58-ring toro gordo. Rum-friendly crowd pleaser.",
    "priceNote": "",
    "sizeNote": ""
  },
  {
    "row": 77,
    "sku": "CUR-08-HOYO-EPICURE",
    "msrpUsd": 0,
    "lengthIn": 4.5,
    "ringGauge": 50,
    "shape": "Petit Robusto",
    "stickSize": "4½ × 50 · Petit Robusto",
    "smokeBand": "short",
    "catalogLine": "Hoyo de Monterrey Epicure Epicure No. 2 · 4½ × 50 · Petit Robusto · Medium · Cuban · — · Notes: cream, cedar, nuts, toast",
    "memberBlurb": "Short Cuban epicure - coffee, cream, and light earth in a 4½-inch petit format. Famous morning Habanos.",
    "priceNote": "Island Cuban; not U.S. retail MSRP.",
    "sizeNote": ""
  },
  {
    "row": 78,
    "sku": "CUR-09-ZINO-CHUBBY",
    "msrpUsd": 18,
    "lengthIn": 4.625,
    "ringGauge": 54,
    "shape": "Robusto",
    "stickSize": "4.625 × 54 · Robusto",
    "smokeBand": "standard",
    "catalogLine": "Davidoff Zino Platinum Crown Series · 4.625 × 54 · Robusto · Medium · Dominican · $18 · Notes: cream, cedar, nuts, toast",
    "memberBlurb": "Davidoff Zino platinum polish - cream, toast, and champagne-friendly elegance in a chubby 54-ring.",
    "priceNote": "",
    "sizeNote": ""
  },
  {
    "row": 79,
    "sku": "CUR-10-UPMANN-M50",
    "msrpUsd": 0,
    "lengthIn": 6.1,
    "ringGauge": 50,
    "shape": "Robusto",
    "stickSize": "6.1 × 50 · Robusto",
    "smokeBand": "long",
    "catalogLine": "H. Upmann Magnum · 6.1 × 50 · Robusto · Medium · Cuban · — · Notes: cedar, wood, earth, leather",
    "memberBlurb": "H. Upmann magnum format - toasted nuts, cedar, and classic medium Cuban character in a 50-ring robusto length.",
    "priceNote": "Island Cuban; not U.S. retail MSRP.",
    "sizeNote": ""
  },
  {
    "row": 80,
    "sku": "CUR-11-VR-UNICO",
    "msrpUsd": 0,
    "lengthIn": 6.125,
    "ringGauge": 52,
    "shape": "Toro",
    "stickSize": "6⅛ × 52 · Toro",
    "smokeBand": "long",
    "catalogLine": "Vegas Robaina Unicos · 6⅛ × 52 · Toro · Medium-Full · Cuban · — · Notes: cedar, wood, earth, leather",
    "memberBlurb": "Robaina family Cuban - earthy sweetness, medium-full body, and toro timing. For Habanos smokers who want more than Hoyo cream.",
    "priceNote": "Island Cuban; not U.S. retail MSRP.",
    "sizeNote": ""
  },
  {
    "row": 81,
    "sku": "CUR-12-PART-LUSI",
    "msrpUsd": 0,
    "lengthIn": 7.625,
    "ringGauge": 49,
    "shape": "Churchill",
    "stickSize": "7.625 × 49 · Churchill",
    "smokeBand": "session",
    "catalogLine": "Partagás Lusitania · 7.625 × 49 · Churchill · Full · Cuban · — · Notes: cedar, wood, earth, leather",
    "memberBlurb": "Legendary Partagas lusitania - pepper, earth, and full Churchill power. One of the reference Cuban large formats.",
    "priceNote": "Island Cuban; not U.S. retail MSRP.",
    "sizeNote": ""
  },
  {
    "row": 82,
    "sku": "CUR-13-PAD-1964-EX",
    "msrpUsd": 19,
    "lengthIn": 5.5,
    "ringGauge": 50,
    "shape": "Robusto",
    "stickSize": "5½ × 50 · Robusto",
    "smokeBand": "standard",
    "catalogLine": "Padron 1964 Anniversary Series · 5½ × 50 · Robusto · Full · Nicaragua · $19 · Notes: cocoa, coffee, earth, dark sweetness",
    "memberBlurb": "Padron 1964 exclusivo - cocoa, coffee, and box-pressed Nicaraguan luxury in a 5½ x 50. Daily-driver anniversary line vs 1926 collector.",
    "priceNote": "",
    "sizeNote": "1964 Exclusivo; CA24-04 is 1926 No. 6; L4-PAD-2000 is daily 2000 line."
  },
  {
    "row": 83,
    "sku": "CUR-14-COHIBA-ROB",
    "msrpUsd": 14,
    "lengthIn": 5.0,
    "ringGauge": 50,
    "shape": "Robusto",
    "stickSize": "5 × 50 · Robusto",
    "smokeBand": "standard",
    "catalogLine": "Cohiba Dominican / Red Dot · 5 × 50 · Robusto · Medium · Dominican · $14 · Notes: cedar, wood, earth, leather",
    "memberBlurb": "The recognizable U.S. Cohiba robusto - Cameroon wrapper, cream, cedar, and black pepper in a 5x50. Heritage name without island Cuban sourcing.",
    "priceNote": "",
    "sizeNote": "Classic Red Dot robusto; HTD-10 is multi-vitola; CA24-20 is Riviera line."
  },
  {
    "row": 84,
    "sku": "CUR-15-RYJ-RR-CH",
    "msrpUsd": 10,
    "lengthIn": 7.0,
    "ringGauge": 48,
    "shape": "Churchill",
    "stickSize": "7 × 48 · Churchill",
    "smokeBand": "session",
    "catalogLine": "Romeo y Julieta Reserva Real · 7 × 48 · Churchill · Medium · Dominican · $10 · Notes: cream, cedar, nuts, toast",
    "memberBlurb": "Reserva Real Churchill - silky Ecuador Connecticut, nuts, and gentle spice in a long easy session. Milder than 1875, crowd-friendly.",
    "priceNote": "",
    "sizeNote": "Distinct from L3-RYJ-1875 (1875 line)."
  },
  {
    "row": 85,
    "sku": "CUR-16-MF-JUDGE-TORO",
    "msrpUsd": 16,
    "lengthIn": 6.0,
    "ringGauge": 52,
    "shape": "Toro",
    "stickSize": "6 × 52 · Toro",
    "smokeBand": "long",
    "catalogLine": "My Father The Judge · 6 × 52 · Toro · Full · Nicaragua · $16 · Notes: cocoa, coffee, earth, dark sweetness",
    "memberBlurb": "The Judge in toro - same Pepín family power as the 2024 COTY grand robusto, but a classic 6x52 format for a full after-dinner arc.",
    "priceNote": "",
    "sizeNote": "Judge toro; CA24-01 is Grand Robusto 6x60 COTY vitola."
  }
]
